djcdata.libs/libstdc++-8baf04f9.so.6.0.28
djcdata.libs/libgcc_s-8b50eaaa.so.1
djcdata-2.1.3.data/scripts/validateDJCFiles.py
djcdata-2.1.3.data/scripts/createDataCollectionFromTD.py
djcdata-2.1.3.data/scripts/convertDJCFromSource.py
djcdata-2.1.3.data/scripts/validateDJCDataCollection.py
djcdata-2.1.3.data/scripts/mergeOrSplitDJCFiles.py
djcdata-2.1.3.dist-info/LICENSE.txt
djcdata-2.1.3.dist-info/WHEEL
djcdata-2.1.3.dist-info/METADATA
djcdata-2.1.3.dist-info/RECORD
djcdata-2.1.3.dist-info/top_level.txt
djcdata/compiled.cpython-310-i386-linux-gnu.so
djcdata/__init__.py
djcdata/DataCollection.py
djcdata/TrainData.py
djcdata/dataPipeline.py
djcdata/torch_interface.py
djcdata/conversion.py
djcdata/stopwatch.py
djcdata/SimpleArray.py
