Metadata-Version: 2.1
Name: djcdata
Version: 2.1.3
Summary: DeepJetCore data formats and pipeline standalone
Home-page: https://github.com/jkiesele/djcdata
Author: Jan Kieseler
Author-email: jan.kieseler@cern.ch
License-File: LICENSE.txt
Requires-Dist: numpy
